{ "teamId": "1610612758"
, "stats":
  { "latest":
    { "seasonYear": 2021
    , "seasonStageId": 2
    , "ppg": "10.1"
    , "rpg": "2.3"
    , "apg": "3.4"
    , "mpg": "25.6"
    , "topg": "1.1"
    , "spg": "0.7"
    , "bpg": "0.3"
    , "tpp": "31.5"
    , "ftp": "56.1"
    , "fgp": "40.5"
    , "assists": "165"
    , "blocks": "15"
    , "steals": "33"
    , "turnovers": "52"
    , "offReb": "25"
    , "defReb": "83"
    , "totReb": "108"
    , "fgm": "201"
    , "fga": "496"
    , "tpm": "62"
    , "tpa": "197"
    , "ftm": "23"
    , "fta": "41"
    , "pFouls": "91"
    , "points": "487"
    , "gamesPlayed": "48"
    , "gamesStarted": "6"
    , "plusMinus": "-396"
    , "min": "1230"
    , "dd2": "0"
    , "td3": "0"
    }
  , "careerSummary":
    { "tpp": "31.5"
    , "ftp": "56.1"
    , "fgp": "40.5"
    , "ppg": "10.1"
    , "rpg": "2.3"
    , "apg": "3.4"
    , "bpg": "0.3"
    , "mpg": "25.6"
    , "spg": "0.7"
    , "assists": "165"
    , "blocks": "15"
    , "steals": "33"
    , "turnovers": "52"
    , "offReb": "25"
    , "defReb": "83"
    , "totReb": "108"
    , "fgm": "201"
    , "fga": "496"
    , "tpm": "62"
    , "tpa": "197"
    , "ftm": "23"
    , "fta": "41"
    , "pFouls": "91"
    , "points": "487"
    , "gamesPlayed": "48"
    , "gamesStarted": "6"
    , "plusMinus": "-132"
    , "min": "1230"
    , "dd2": "0"
    , "td3": "0"
    }
  , "regularSeason":
    { "season":
      [ { "seasonYear": 2021
        , "teams":
          [ { "teamId": "1610612758"
            , "ppg": "10.1"
            , "rpg": "2.3"
            , "apg": "3.4"
            , "mpg": "25.6"
            , "topg": "1.1"
            , "spg": "0.7"
            , "bpg": "0.3"
            , "tpp": "31.5"
            , "ftp": "56.1"
            , "fgp": "40.5"
            , "assists": "165"
            , "blocks": "15"
            , "steals": "33"
            , "turnovers": "52"
            , "offReb": "25"
            , "defReb": "83"
            , "totReb": "108"
            , "fgm": "201"
            , "fga": "496"
            , "tpm": "62"
            , "tpa": "197"
            , "ftm": "23"
            , "fta": "41"
            , "pFouls": "91"
            , "points": "487"
            , "gamesPlayed": "48"
            , "gamesStarted": "6"
            , "plusMinus": "-396"
            , "min": "1230"
            , "dd2": "0"
            , "td3": "0"
            }
          ]
        , "total":
          { "ppg": "10.1"
          , "rpg": "2.3"
          , "apg": "3.4"
          , "mpg": "25.6"
          , "topg": "1.1"
          , "spg": "0.7"
          , "bpg": "0.3"
          , "tpp": "31.5"
          , "ftp": "56.1"
          , "fgp": "40.5"
          , "assists": "165"
          , "blocks": "15"
          , "steals": "33"
          , "turnovers": "52"
          , "offReb": "25"
          , "defReb": "83"
          , "totReb": "108"
          , "fgm": "201"
          , "fga": "496"
          , "tpm": "62"
          , "tpa": "197"
          , "ftm": "23"
          , "fta": "41"
          , "pFouls": "91"
          , "points": "487"
          , "gamesPlayed": "48"
          , "gamesStarted": "6"
          , "plusMinus": "-396"
          , "min": "1230"
          , "dd2": "0"
          , "td3": "0"
          }
        }
      ]
    }
  }
}