{ "teamId": "1610612753"
, "stats":
  { "latest":
    { "seasonYear": 2021
    , "seasonStageId": 2
    , "ppg": "2.5"
    , "rpg": "1.4"
    , "apg": "0.7"
    , "mpg": "8.9"
    , "topg": "0.3"
    , "spg": "0.2"
    , "bpg": "0"
    , "tpp": "28.6"
    , "ftp": "80"
    , "fgp": "35.1"
    , "assists": "15"
    , "blocks": "1"
    , "steals": "5"
    , "turnovers": "6"
    , "offReb": "8"
    , "defReb": "22"
    , "totReb": "30"
    , "fgm": "20"
    , "fga": "57"
    , "tpm": "8"
    , "tpa": "28"
    , "ftm": "8"
    , "fta": "10"
    , "pFouls": "22"
    , "points": "56"
    , "gamesPlayed": "22"
    , "gamesStarted": "0"
    , "plusMinus": "-66"
    , "min": "196"
    , "dd2": "0"
    , "td3": "0"
    }
  , "careerSummary":
    { "tpp": "30.8"
    , "ftp": "75.9"
    , "fgp": "37.7"
    , "ppg": "3.7"
    , "rpg": "1.8"
    , "apg": "0.8"
    , "bpg": "0.1"
    , "mpg": "11.3"
    , "spg": "0.2"
    , "assists": "36"
    , "blocks": "5"
    , "steals": "9"
    , "turnovers": "20"
    , "offReb": "21"
    , "defReb": "59"
    , "totReb": "80"
    , "fgm": "61"
    , "fga": "162"
    , "tpm": "20"
    , "tpa": "65"
    , "ftm": "22"
    , "fta": "29"
    , "pFouls": "47"
    , "points": "164"
    , "gamesPlayed": "44"
    , "gamesStarted": "0"
    , "plusMinus": "-60"
    , "min": "498"
    , "dd2": "0"
    , "td3": "0"
    }
  , "regularSeason":
    { "season":
      [ { "seasonYear": 2021
        , "teams":
          [ { "teamId": "1610612753"
            , "ppg": "2.5"
            , "rpg": "1.4"
            , "apg": "0.7"
            , "mpg": "8.9"
            , "topg": "0.3"
            , "spg": "0.2"
            , "bpg": "0"
            , "tpp": "28.6"
            , "ftp": "80"
            , "fgp": "35.1"
            , "assists": "15"
            , "blocks": "1"
            , "steals": "5"
            , "turnovers": "6"
            , "offReb": "8"
            , "defReb": "22"
            , "totReb": "30"
            , "fgm": "20"
            , "fga": "57"
            , "tpm": "8"
            , "tpa": "28"
            , "ftm": "8"
            , "fta": "10"
            , "pFouls": "22"
            , "points": "56"
            , "gamesPlayed": "22"
            , "gamesStarted": "0"
            , "plusMinus": "-66"
            , "min": "196"
            , "dd2": "0"
            , "td3": "0"
            }
          ]
        , "total":
          { "ppg": "2.5"
          , "rpg": "1.4"
          , "apg": "0.7"
          , "mpg": "8.9"
          , "topg": "0.3"
          , "spg": "0.2"
          , "bpg": "0"
          , "tpp": "28.6"
          , "ftp": "80"
          , "fgp": "35.1"
          , "assists": "15"
          , "blocks": "1"
          , "steals": "5"
          , "turnovers": "6"
          , "offReb": "8"
          , "defReb": "22"
          , "totReb": "30"
          , "fgm": "20"
          , "fga": "57"
          , "tpm": "8"
          , "tpa": "28"
          , "ftm": "8"
          , "fta": "10"
          , "pFouls": "22"
          , "points": "56"
          , "gamesPlayed": "22"
          , "gamesStarted": "0"
          , "plusMinus": "-66"
          , "min": "196"
          , "dd2": "0"
          , "td3": "0"
          }
        }
      , { "seasonYear": 2020
        , "teams":
          [ { "teamId": "0"
            , "ppg": "7"
            , "rpg": "3.5"
            , "apg": "1.3"
            , "mpg": "19.2"
            , "topg": "0.9"
            , "spg": "0.3"
            , "bpg": "0.2"
            , "tpp": "39.3"
            , "ftp": "71.4"
            , "fgp": "42.2"
            , "assists": "17"
            , "blocks": "3"
            , "steals": "4"
            , "turnovers": "12"
            , "offReb": "11"
            , "defReb": "34"
            , "totReb": "45"
            , "fgm": "35"
            , "fga": "83"
            , "tpm": "11"
            , "tpa": "28"
            , "ftm": "10"
            , "fta": "14"
            , "pFouls": "22"
            , "points": "91"
            , "gamesPlayed": "13"
            , "gamesStarted": "0"
            , "plusMinus": "-135"
            , "min": "248"
            , "dd2": "0"
            , "td3": "0"
            }
          , { "teamId": "1610612753"
            , "ppg": "11.1"
            , "rpg": "5.1"
            , "apg": "2"
            , "mpg": "29.3"
            , "topg": "1.4"
            , "spg": "0.5"
            , "bpg": "0.4"
            , "tpp": "40.7"
            , "ftp": "66.7"
            , "fgp": "44.3"
            , "assists": "16"
            , "blocks": "3"
            , "steals": "4"
            , "turnovers": "11"
            , "offReb": "10"
            , "defReb": "31"
            , "totReb": "41"
            , "fgm": "35"
            , "fga": "79"
            , "tpm": "11"
            , "tpa": "27"
            , "ftm": "8"
            , "fta": "12"
            , "pFouls": "22"
            , "points": "89"
            , "gamesPlayed": "8"
            , "gamesStarted": "0"
            , "plusMinus": "-135"
            , "min": "233"
            , "dd2": "0"
            , "td3": "0"
            }
          , { "teamId": "1610612755"
            , "ppg": "0"
            , "rpg": "2"
            , "apg": "0"
            , "mpg": "8"
            , "topg": "0"
            , "spg": "0"
            , "bpg": "0"
            , "tpp": "0"
            , "ftp": "0"
            , "fgp": "0"
            , "assists": "0"
            , "blocks": "0"
            , "steals": "0"
            , "turnovers": "0"
            , "offReb": "0"
            , "defReb": "2"
            , "totReb": "2"
            , "fgm": "0"
            , "fga": "3"
            , "tpm": "0"
            , "tpa": "1"
            , "ftm": "0"
            , "fta": "0"
            , "pFouls": "0"
            , "points": "0"
            , "gamesPlayed": "1"
            , "gamesStarted": "0"
            , "plusMinus": "30"
            , "min": "7"
            , "dd2": "0"
            , "td3": "0"
            }
          , { "teamId": "1610612752"
            , "ppg": "0.5"
            , "rpg": "0.5"
            , "apg": "0.3"
            , "mpg": "1.8"
            , "topg": "0.2"
            , "spg": "0"
            , "bpg": "0"
            , "tpp": "0"
            , "ftp": "100"
            , "fgp": "0"
            , "assists": "1"
            , "blocks": "0"
            , "steals": "0"
            , "turnovers": "1"
            , "offReb": "1"
            , "defReb": "1"
            , "totReb": "2"
            , "fgm": "0"
            , "fga": "1"
            , "tpm": "0"
            , "tpa": "0"
            , "ftm": "2"
            , "fta": "2"
            , "pFouls": "0"
            , "points": "2"
            , "gamesPlayed": "4"
            , "gamesStarted": "0"
            , "plusMinus": "-30"
            , "min": "7"
            , "dd2": "0"
            , "td3": "0"
            }
          ]
        , "total":
          { "ppg": "7"
          , "rpg": "3.5"
          , "apg": "1.3"
          , "mpg": "19.2"
          , "topg": "0.9"
          , "spg": "0.3"
          , "bpg": "0.2"
          , "tpp": "39.3"
          , "ftp": "71.4"
          , "fgp": "42.2"
          , "assists": "17"
          , "blocks": "3"
          , "steals": "4"
          , "turnovers": "12"
          , "offReb": "11"
          , "defReb": "34"
          , "totReb": "45"
          , "fgm": "35"
          , "fga": "83"
          , "tpm": "11"
          , "tpa": "28"
          , "ftm": "10"
          , "fta": "14"
          , "pFouls": "22"
          , "points": "91"
          , "gamesPlayed": "13"
          , "gamesStarted": "0"
          , "plusMinus": "-135"
          , "min": "248"
          , "dd2": "0"
          , "td3": "0"
          }
        }
      , { "seasonYear": 2019
        , "teams":
          [ { "teamId": "1610612752"
            , "ppg": "1.9"
            , "rpg": "0.6"
            , "apg": "0.4"
            , "mpg": "5.9"
            , "topg": "0.2"
            , "spg": "0"
            , "bpg": "0.1"
            , "tpp": "11.1"
            , "ftp": "80"
            , "fgp": "27.3"
            , "assists": "4"
            , "blocks": "1"
            , "steals": "0"
            , "turnovers": "2"
            , "offReb": "2"
            , "defReb": "3"
            , "totReb": "5"
            , "fgm": "6"
            , "fga": "22"
            , "tpm": "1"
            , "tpa": "9"
            , "ftm": "4"
            , "fta": "5"
            , "pFouls": "3"
            , "points": "17"
            , "gamesPlayed": "9"
            , "gamesStarted": "0"
            , "plusMinus": "-44"
            , "min": "53"
            , "dd2": "0"
            , "td3": "0"
            }
          ]
        , "total":
          { "ppg": "1.9"
          , "rpg": "0.6"
          , "apg": "0.4"
          , "mpg": "5.9"
          , "topg": "0.2"
          , "spg": "0"
          , "bpg": "0.1"
          , "tpp": "11.1"
          , "ftp": "80"
          , "fgp": "27.3"
          , "assists": "4"
          , "blocks": "1"
          , "steals": "0"
          , "turnovers": "2"
          , "offReb": "2"
          , "defReb": "3"
          , "totReb": "5"
          , "fgm": "6"
          , "fga": "22"
          , "tpm": "1"
          , "tpa": "9"
          , "ftm": "4"
          , "fta": "5"
          , "pFouls": "3"
          , "points": "17"
          , "gamesPlayed": "9"
          , "gamesStarted": "0"
          , "plusMinus": "-44"
          , "min": "53"
          , "dd2": "0"
          , "td3": "0"
          }
        }
      ]
    }
  }
}