{ "teamId": "1610612765"
, "stats":
  { "latest":
    { "seasonYear": 2021
    , "seasonStageId": 2
    , "ppg": "15.6"
    , "rpg": "5.8"
    , "apg": "2.7"
    , "mpg": "33.5"
    , "topg": "1.4"
    , "spg": "0.9"
    , "bpg": "0.2"
    , "tpp": "33.5"
    , "ftp": "82.8"
    , "fgp": "38.5"
    , "assists": "138"
    , "blocks": "10"
    , "steals": "48"
    , "turnovers": "70"
    , "offReb": "71"
    , "defReb": "228"
    , "totReb": "299"
    , "fgm": "280"
    , "fga": "728"
    , "tpm": "127"
    , "tpa": "379"
    , "ftm": "125"
    , "fta": "151"
    , "pFouls": "88"
    , "points": "812"
    , "gamesPlayed": "52"
    , "gamesStarted": "52"
    , "plusMinus": "-762"
    , "min": "1742"
    , "dd2": "5"
    , "td3": "0"
    }
  , "careerSummary":
    { "tpp": "36"
    , "ftp": "83.6"
    , "fgp": "39.4"
    , "ppg": "13.7"
    , "rpg": "5.1"
    , "apg": "1.9"
    , "bpg": "0.2"
    , "mpg": "29.9"
    , "spg": "0.8"
    , "assists": "233"
    , "blocks": "24"
    , "steals": "100"
    , "turnovers": "130"
    , "offReb": "114"
    , "defReb": "503"
    , "totReb": "617"
    , "fgm": "559"
    , "fga": "1419"
    , "tpm": "302"
    , "tpa": "839"
    , "ftm": "249"
    , "fta": "298"
    , "pFouls": "198"
    , "points": "1669"
    , "gamesPlayed": "122"
    , "gamesStarted": "105"
    , "plusMinus": "-595"
    , "min": "3651"
    , "dd2": "8"
    , "td3": "0"
    }
  , "regularSeason":
    { "season":
      [ { "seasonYear": 2021
        , "teams":
          [ { "teamId": "1610612765"
            , "ppg": "15.6"
            , "rpg": "5.8"
            , "apg": "2.7"
            , "mpg": "33.5"
            , "topg": "1.4"
            , "spg": "0.9"
            , "bpg": "0.2"
            , "tpp": "33.5"
            , "ftp": "82.8"
            , "fgp": "38.5"
            , "assists": "138"
            , "blocks": "10"
            , "steals": "48"
            , "turnovers": "70"
            , "offReb": "71"
            , "defReb": "228"
            , "totReb": "299"
            , "fgm": "280"
            , "fga": "728"
            , "tpm": "127"
            , "tpa": "379"
            , "ftm": "125"
            , "fta": "151"
            , "pFouls": "88"
            , "points": "812"
            , "gamesPlayed": "52"
            , "gamesStarted": "52"
            , "plusMinus": "-762"
            , "min": "1742"
            , "dd2": "5"
            , "td3": "0"
            }
          ]
        , "total":
          { "ppg": "15.6"
          , "rpg": "5.8"
          , "apg": "2.7"
          , "mpg": "33.5"
          , "topg": "1.4"
          , "spg": "0.9"
          , "bpg": "0.2"
          , "tpp": "33.5"
          , "ftp": "82.8"
          , "fgp": "38.5"
          , "assists": "138"
          , "blocks": "10"
          , "steals": "48"
          , "turnovers": "70"
          , "offReb": "71"
          , "defReb": "228"
          , "totReb": "299"
          , "fgm": "280"
          , "fga": "728"
          , "tpm": "127"
          , "tpa": "379"
          , "ftm": "125"
          , "fta": "151"
          , "pFouls": "88"
          , "points": "812"
          , "gamesPlayed": "52"
          , "gamesStarted": "52"
          , "plusMinus": "-762"
          , "min": "1742"
          , "dd2": "5"
          , "td3": "0"
          }
        }
      , { "seasonYear": 2020
        , "teams":
          [ { "teamId": "1610612765"
            , "ppg": "12.2"
            , "rpg": "4.5"
            , "apg": "1.4"
            , "mpg": "27.3"
            , "topg": "0.9"
            , "spg": "0.7"
            , "bpg": "0.2"
            , "tpp": "38"
            , "ftp": "84.4"
            , "fgp": "40.4"
            , "assists": "95"
            , "blocks": "14"
            , "steals": "52"
            , "turnovers": "60"
            , "offReb": "43"
            , "defReb": "275"
            , "totReb": "318"
            , "fgm": "279"
            , "fga": "691"
            , "tpm": "175"
            , "tpa": "460"
            , "ftm": "124"
            , "fta": "147"
            , "pFouls": "110"
            , "points": "857"
            , "gamesPlayed": "70"
            , "gamesStarted": "53"
            , "plusMinus": "-214"
            , "min": "1909"
            , "dd2": "3"
            , "td3": "0"
            }
          ]
        , "total":
          { "ppg": "12.2"
          , "rpg": "4.5"
          , "apg": "1.4"
          , "mpg": "27.3"
          , "topg": "0.9"
          , "spg": "0.7"
          , "bpg": "0.2"
          , "tpp": "38"
          , "ftp": "84.4"
          , "fgp": "40.4"
          , "assists": "95"
          , "blocks": "14"
          , "steals": "52"
          , "turnovers": "60"
          , "offReb": "43"
          , "defReb": "275"
          , "totReb": "318"
          , "fgm": "279"
          , "fga": "691"
          , "tpm": "175"
          , "tpa": "460"
          , "ftm": "124"
          , "fta": "147"
          , "pFouls": "110"
          , "points": "857"
          , "gamesPlayed": "70"
          , "gamesStarted": "53"
          , "plusMinus": "-214"
          , "min": "1909"
          , "dd2": "3"
          , "td3": "0"
          }
        }
      ]
    }
  }
}