{ "teamId": "1610612758"
, "stats":
  { "latest":
    { "seasonYear": 2021
    , "seasonStageId": 2
    , "ppg": "14.3"
    , "rpg": "3.9"
    , "apg": "7.2"
    , "mpg": "34.3"
    , "topg": "2.2"
    , "spg": "1.7"
    , "bpg": "0.7"
    , "tpp": "41.6"
    , "ftp": "83.2"
    , "fgp": "45.9"
    , "assists": "362"
    , "blocks": "33"
    , "steals": "84"
    , "turnovers": "111"
    , "offReb": "37"
    , "defReb": "156"
    , "totReb": "193"
    , "fgm": "263"
    , "fga": "573"
    , "tpm": "104"
    , "tpa": "250"
    , "ftm": "84"
    , "fta": "101"
    , "pFouls": "70"
    , "points": "714"
    , "gamesPlayed": "50"
    , "gamesStarted": "50"
    , "plusMinus": "-229"
    , "min": "1717"
    , "dd2": "13"
    , "td3": "0"
    }
  , "careerSummary":
    { "tpp": "41.2"
    , "ftp": "84.1"
    , "fgp": "46.6"
    , "ppg": "13.6"
    , "rpg": "3.4"
    , "apg": "6.2"
    , "bpg": "0.6"
    , "mpg": "32.1"
    , "spg": "1.5"
    , "assists": "671"
    , "blocks": "61"
    , "steals": "161"
    , "turnovers": "203"
    , "offReb": "76"
    , "defReb": "290"
    , "totReb": "366"
    , "fgm": "555"
    , "fga": "1192"
    , "tpm": "225"
    , "tpa": "546"
    , "ftm": "132"
    , "fta": "157"
    , "pFouls": "153"
    , "points": "1467"
    , "gamesPlayed": "108"
    , "gamesStarted": "70"
    , "plusMinus": "-408"
    , "min": "3462"
    , "dd2": "18"
    , "td3": "0"
    }
  , "regularSeason":
    { "season":
      [ { "seasonYear": 2021
        , "teams":
          [ { "teamId": "1610612758"
            , "ppg": "14.3"
            , "rpg": "3.9"
            , "apg": "7.2"
            , "mpg": "34.3"
            , "topg": "2.2"
            , "spg": "1.7"
            , "bpg": "0.7"
            , "tpp": "41.6"
            , "ftp": "83.2"
            , "fgp": "45.9"
            , "assists": "362"
            , "blocks": "33"
            , "steals": "84"
            , "turnovers": "111"
            , "offReb": "37"
            , "defReb": "156"
            , "totReb": "193"
            , "fgm": "263"
            , "fga": "573"
            , "tpm": "104"
            , "tpa": "250"
            , "ftm": "84"
            , "fta": "101"
            , "pFouls": "70"
            , "points": "714"
            , "gamesPlayed": "50"
            , "gamesStarted": "50"
            , "plusMinus": "-229"
            , "min": "1717"
            , "dd2": "13"
            , "td3": "0"
            }
          ]
        , "total":
          { "ppg": "14.3"
          , "rpg": "3.9"
          , "apg": "7.2"
          , "mpg": "34.3"
          , "topg": "2.2"
          , "spg": "1.7"
          , "bpg": "0.7"
          , "tpp": "41.6"
          , "ftp": "83.2"
          , "fgp": "45.9"
          , "assists": "362"
          , "blocks": "33"
          , "steals": "84"
          , "turnovers": "111"
          , "offReb": "37"
          , "defReb": "156"
          , "totReb": "193"
          , "fgm": "263"
          , "fga": "573"
          , "tpm": "104"
          , "tpa": "250"
          , "ftm": "84"
          , "fta": "101"
          , "pFouls": "70"
          , "points": "714"
          , "gamesPlayed": "50"
          , "gamesStarted": "50"
          , "plusMinus": "-229"
          , "min": "1717"
          , "dd2": "13"
          , "td3": "0"
          }
        }
      , { "seasonYear": 2020
        , "teams":
          [ { "teamId": "1610612758"
            , "ppg": "13"
            , "rpg": "3"
            , "apg": "5.3"
            , "mpg": "30.1"
            , "topg": "1.6"
            , "spg": "1.3"
            , "bpg": "0.5"
            , "tpp": "40.9"
            , "ftp": "85.7"
            , "fgp": "47.2"
            , "assists": "309"
            , "blocks": "28"
            , "steals": "77"
            , "turnovers": "92"
            , "offReb": "39"
            , "defReb": "134"
            , "totReb": "173"
            , "fgm": "292"
            , "fga": "619"
            , "tpm": "121"
            , "tpa": "296"
            , "ftm": "48"
            , "fta": "56"
            , "pFouls": "83"
            , "points": "753"
            , "gamesPlayed": "58"
            , "gamesStarted": "20"
            , "plusMinus": "-179"
            , "min": "1745"
            , "dd2": "5"
            , "td3": "0"
            }
          ]
        , "total":
          { "ppg": "13"
          , "rpg": "3"
          , "apg": "5.3"
          , "mpg": "30.1"
          , "topg": "1.6"
          , "spg": "1.3"
          , "bpg": "0.5"
          , "tpp": "40.9"
          , "ftp": "85.7"
          , "fgp": "47.2"
          , "assists": "309"
          , "blocks": "28"
          , "steals": "77"
          , "turnovers": "92"
          , "offReb": "39"
          , "defReb": "134"
          , "totReb": "173"
          , "fgm": "292"
          , "fga": "619"
          , "tpm": "121"
          , "tpa": "296"
          , "ftm": "48"
          , "fta": "56"
          , "pFouls": "83"
          , "points": "753"
          , "gamesPlayed": "58"
          , "gamesStarted": "20"
          , "plusMinus": "-179"
          , "min": "1745"
          , "dd2": "5"
          , "td3": "0"
          }
        }
      ]
    }
  }
}